{"height":10,"width":20,"startX":1,"startY":8,"endX":18,"endY":8,"tileSize":16,"tiles":[{"type":0,"spriteId":5,"sides":[0,0,0,0]},{"type":0,"spriteId":9,"sides":[0,0,1,0]},{"type":0,"spriteId":9,"sides":[0,0,1,0]},{"type":0,"spriteId":9,"sides":[0,0,1,0]},{"type":0,"spriteId":9,"sides":[0,0,1,0]},{"type":0,"spriteId":9,"sides":[0,0,1,0]},{"type":0,"spriteId":9,"sides":[0,0,1,0]},{"type":0,"spriteId":9,"sides":[0,0,1,0]},{"type":0,"spriteId":9,"sides":[0,0,1,0]},{"type":0,"spriteId":9,"sides":[0,0,1,0]},{"type":0,"spriteId":9,"sides":[0,0,1,0]},{"type":0,"spriteId":9,"sides":[0,0,1,0]},{"type":0,"spriteId":9,"sides":[0,0,1,0]},{"type":0,"spriteId":9,"sides":[0,0,1,0]},{"type":0,"spriteId":9,"sides":[0,0,1,0]},{"type":0,"spriteId":9,"sides":[0,0,1,0]},{"type":0,"spriteId":9,"sides":[0,0,1,0]},{"type":0,"spriteId":9,"sides":[0,0,1,0]},{"type":0,"spriteId":9,"sides":[0,0,1,0]},{"type":0,"spriteId":5,"sides":[0,0,0,0]},{"type":0,"spriteId":6,"sides":[0,1,0,0]},false,false,false,false,false,false,false,false,false,false,false,false,false,false,false,false,false,false,{"type":0,"spriteId":4,"sides":[0,0,0,1]},{"type":0,"spriteId":6,"sides":[0,1,0,0]},false,false,false,false,false,false,false,false,false,false,false,false,false,false,false,false,false,false,{"type":0,"spriteId":4,"sides":[0,0,0,1]},{"type":0,"spriteId":6,"sides":[0,1,0,0]},false,false,false,false,false,false,false,false,false,false,false,false,false,false,false,false,false,false,{"type":0,"spriteId":4,"sides":[0,0,0,1]},{"type":0,"spriteId":6,"sides":[0,1,0,0]},false,false,false,false,false,false,false,false,false,false,false,false,false,false,false,false,false,false,{"type":0,"spriteId":4,"sides":[0,0,0,1]},{"type":0,"spriteId":6,"sides":[0,1,0,0]},false,false,false,false,false,false,false,false,false,false,false,false,false,false,false,false,false,false,{"type":0,"spriteId":4,"sides":[0,0,0,1]},{"type":0,"spriteId":6,"sides":[0,1,0,0]},false,false,false,false,false,false,false,false,false,false,false,false,false,false,false,false,false,false,{"type":0,"spriteId":4,"sides":[0,0,0,1]},{"type":0,"spriteId":6,"sides":[0,1,0,0]},false,false,false,false,false,false,false,false,false,false,false,false,false,false,false,false,false,false,{"type":0,"spriteId":4,"sides":[0,0,0,1]},{"type":0,"spriteId":6,"sides":[0,1,0,0]},{"type":2},false,false,false,false,false,false,false,false,false,false,false,false,false,false,false,false,{"type":4},{"type":0,"spriteId":4,"sides":[0,0,0,1]},{"type":0,"spriteId":5,"sides":[0,0,0,0]},{"type":0,"spriteId":1,"sides":[1,0,0,0]},{"type":0,"spriteId":1,"sides":[1,0,0,0]},{"type":0,"spriteId":1,"sides":[1,0,0,0]},{"type":0,"spriteId":1,"sides":[1,0,0,0]},{"type":0,"spriteId":1,"sides":[1,0,0,0]},{"type":0,"spriteId":1,"sides":[1,0,0,0]},{"type":0,"spriteId":1,"sides":[1,0,0,0]},{"type":0,"spriteId":1,"sides":[1,0,0,0]},{"type":0,"spriteId":1,"sides":[1,0,0,0]},{"type":0,"spriteId":1,"sides":[1,0,0,0]},{"type":0,"spriteId":1,"sides":[1,0,0,0]},{"type":0,"spriteId":1,"sides":[1,0,0,0]},{"type":0,"spriteId":1,"sides":[1,0,0,0]},{"type":0,"spriteId":1,"sides":[1,0,0,0]},{"type":0,"spriteId":1,"sides":[1,0,0,0]},{"type":0,"spriteId":1,"sides":[1,0,0,0]},{"type":0,"spriteId":1,"sides":[1,0,0,0]},{"type":0,"spriteId":1,"sides":[1,0,0,0]},{"type":0,"spriteId":5,"sides":[0,0,0,0]}]}